tasks/__init__.py
tasks/docker.py
tasks/py.py
tasks/test.py
tmpld/__init__.py
tmpld/cli/__init__.py
tmpld/cli/handlers.py
tmpld/cli/loaders.py
tmpld/cli/main.py
tmpld/cli/util.py
tmpld/core/__init__.py
tmpld/core/environment.py
tmpld/core/filters.py
tmpld/core/frontmatter.py
tmpld/core/tags.py
tmpld/core/template.py
tmpld/core/util.py
tmpld-0.3.0.dist-info/METADATA
tmpld-0.3.0.dist-info/RECORD
tmpld-0.3.0.dist-info/WHEEL
tmpld-0.3.0.dist-info/entry_points.txt
tmpld-0.3.0.dist-info/top_level.txt
